MANIFEST.in
README.rst
setup.py
src/ap/__init__.py
src/ap.egg-info/PKG-INFO
src/ap.egg-info/SOURCES.txt
src/ap.egg-info/dependency_links.txt
src/ap.egg-info/entry_points.txt
src/ap.egg-info/requires.txt
src/ap.egg-info/top_level.txt