Metadata-Version: 1.1
Name: ap
Version: 0.1.2
Summary: AP powers-up commands with AWS profile, assume-role and MFA functionality.
Home-page: https://github.com/nathforge/ap
Author: Nathan Reynolds
Author-email: email@nreynolds.co.uk
License: UNKNOWN
Platform: UNKNOWN
Classifier: Development Status :: 4 - Beta
Classifier: Intended Audience :: Developers
Classifier: Topic :: Software Development
Classifier: License :: OSI Approved :: MIT License
Classifier: Programming Language :: Python :: 2.7
Classifier: Programming Language :: Python :: 3.5
